setup.py
src/quinoa/__init__.py
src/quinoa/dicebot.py
src/quinoa/quinoa.py
src/quinoa/regdict.py
src/quinoa.egg-info/PKG-INFO
src/quinoa.egg-info/SOURCES.txt
src/quinoa.egg-info/dependency_links.txt
src/quinoa.egg-info/requires.txt
src/quinoa.egg-info/top_level.txt